snappy_15_knots/__init__.py
snappy_15_knots/database.py
snappy_15_knots/test.py
snappy_15_knots/sqlite_files/15_knots.sqlite
snappy_15_knots/sqlite_files/__init__.py
snappy_15_knots/sqlite_files/make_sqlite_db.py
snappy_15_knots-1.2.1.dist-info/METADATA
snappy_15_knots-1.2.1.dist-info/WHEEL
snappy_15_knots-1.2.1.dist-info/top_level.txt
snappy_15_knots-1.2.1.dist-info/RECORD
