Metadata-Version: 2.1
Name: snappy_15_knots
Version: 1.2.1
Summary: Database of snappy manifolds
Home-page: https://github.com/3-manifolds/snappy_15_knots
Author: Marc Culler and Nathan M. Dunfield and Mattias Goerner and Malik Obeidin
Author-email: snappy-help@computop.org
License: GPLv2+
Classifier: Development Status :: 5 - Production/Stable
Classifier: Intended Audience :: Science/Research
Classifier: License :: OSI Approved :: GNU General Public License v2 or later (GPLv2+)
Classifier: Operating System :: OS Independent
Classifier: Programming Language :: C
Classifier: Programming Language :: Cython
Classifier: Programming Language :: Python
Classifier: Topic :: Scientific/Engineering :: Mathematics
Requires-Dist: snappy-manifolds
